npsn/__init__.py
npsn/dg.py
npsn/lhs_gen.py
npsn/nn.py
npsn/pp.py
npsn-0.1.dist-info/METADATA
npsn-0.1.dist-info/WHEEL
npsn-0.1.dist-info/top_level.txt
npsn-0.1.dist-info/RECORD
