Metadata-Version: 2.1
Name: npsn
Version: 0.1
Summary: Nuclear Power Surrogate Network
Home-page: https://github.com/a-jd/npsn
Author: Akshay J. Dave
Author-email: akshayjd@mit.edu
License: UNKNOWN
Platform: UNKNOWN
Classifier: Programming Language :: Python :: 3
Classifier: License :: OSI Approved :: MIT License
Classifier: Operating System :: OS Independent
Requires-Python: >=3.6
Requires-Dist: tensorflow (==2.2.0)
Requires-Dist: hyperopt (==0.2.4)
Requires-Dist: scikit-learn (==0.23.1)
Requires-Dist: pydoe (==0.3.8)
Requires-Dist: tables (==3.6.1)
